Metadata-Version: 2.4
Name: iflow-mcp_user-feedback-mcp
Version: 0.1.0
Summary: Add your description here
Requires-Python: >=3.11
License-File: LICENSE
Requires-Dist: fastmcp>=0.4.1
Requires-Dist: psutil>=7.0.0
Requires-Dist: pyside6>=6.8.2.1
Dynamic: license-file
